confluence_utils/__init__.py
confluence_utils/cli.py
confluence_utils/confluence_directives.py
confluence_utils/confluence_renderer.py
confluence_utils/markdown_file.py
confluence_utils/markdown_parser.py
confluence_utils-0.5.0.dist-info/entry_points.txt
confluence_utils-0.5.0.dist-info/LICENSE
confluence_utils-0.5.0.dist-info/WHEEL
confluence_utils-0.5.0.dist-info/METADATA
confluence_utils-0.5.0.dist-info/RECORD
